ahkpy/Python.ahk
ahkpy/__init__.py
ahkpy/__main__.py
ahkpy/block_input.py
ahkpy/clipboard.py
ahkpy/colors.py
ahkpy/exceptions.py
ahkpy/flow.py
ahkpy/hotkey.py
ahkpy/hotkey_context.py
ahkpy/hotstring.py
ahkpy/key_state.py
ahkpy/launcher.py
ahkpy/main.py
ahkpy/menu.py
ahkpy/message_box.py
ahkpy/mouse.py
ahkpy/remap_key.py
ahkpy/sending.py
ahkpy/settings.py
ahkpy/timer.py
ahkpy/tooltip.py
ahkpy/unset.py
ahkpy/window.py
ahkpy/window_message.py
ahkpy/Lib/Commands.ahk
ahkpy/Lib/PythonDll.ahk
ahkpy/Lib/StdoutToVar_CreateProcess.ahk
AutoHotkey.py-0.2.dist-info/LICENSE.md
AutoHotkey.py-0.2.dist-info/METADATA
AutoHotkey.py-0.2.dist-info/WHEEL
AutoHotkey.py-0.2.dist-info/entry_points.txt
AutoHotkey.py-0.2.dist-info/top_level.txt
AutoHotkey.py-0.2.dist-info/RECORD
