Metadata-Version: 2.1
Name: AutoHotkey.py
Version: 0.2
Summary: Write AutoHotkey scripts in Python
Author-email: Sviatoslav Abakumov <dust.harvesting@gmail.com>
License: BSD-3-Clause
Project-URL: Documentation, https://ahkpy.readthedocs.io/en/latest/
Project-URL: Changelog, https://github.com/Perlence/AutoHotkey.py/blob/master/CHANGES.md
Project-URL: Source Code, https://github.com/Perlence/AutoHotkey.py
Project-URL: Issue Tracker, https://github.com/Perlence/AutoHotkey.py/issues
Classifier: Development Status :: 4 - Beta
Classifier: Environment :: Console
Classifier: Intended Audience :: Developers
Classifier: License :: OSI Approved :: BSD License
Classifier: Operating System :: Microsoft :: Windows
Classifier: Programming Language :: Python :: 3
Classifier: Programming Language :: Python :: 3.8
Classifier: Programming Language :: Python :: 3.9
Classifier: Programming Language :: Python :: 3.10
Classifier: Programming Language :: Python :: 3.11
Classifier: Programming Language :: Python :: Implementation :: CPython
Requires-Python: >=3.8
License-File: LICENSE.md
